mujoco_controllers/README.md
mujoco_controllers/__init__.py
mujoco_controllers/build_env.py
mujoco_controllers/config/arena/cameras/transporter_data_collection.yaml
mujoco_controllers/config/arena/props/default.yaml
mujoco_controllers/config/arena/props/single_block.yaml
mujoco_controllers/config/arena/rearrangement_table.yaml
mujoco_controllers/config/itl_rearrangement.yaml
mujoco_controllers/config/robots/arm/actuator_config/intvelocity.yaml
mujoco_controllers/config/robots/arm/actuator_config/motor.yaml
mujoco_controllers/config/robots/arm/actuator_config/velocity.yaml
mujoco_controllers/config/robots/arm/controller_config/diffik.yaml
mujoco_controllers/config/robots/arm/controller_config/osc.yaml
mujoco_controllers/config/robots/arm/franka_emika_panda.yaml
mujoco_controllers/config/robots/arm/sensor_config/position.yaml
mujoco_controllers/config/robots/end_effector/actuator_config/default.yaml
mujoco_controllers/config/robots/end_effector/controller_config/min_max.yaml
mujoco_controllers/config/robots/end_effector/robotiq_2f85.yaml
mujoco_controllers/config/robots/end_effector/sensor_config/default.yaml
mujoco_controllers/config/robots/franka_robotiq_2f85.yaml
mujoco_controllers/config/task/itl_rearrangement.yaml
mujoco_controllers/diffik.py
mujoco_controllers/min_max.py
mujoco_controllers/models/__init__.py
mujoco_controllers/models/arenas/__init__.py
mujoco_controllers/models/arenas/empty.py
mujoco_controllers/models/arenas/empty_assets/arena.xml
mujoco_controllers/models/arms/__init__.py
mujoco_controllers/models/arms/franka_emika.py
mujoco_controllers/models/arms/robot_arm.py
mujoco_controllers/models/end_effectors/__init__.py
mujoco_controllers/models/end_effectors/robot_hand.py
mujoco_controllers/models/end_effectors/robotiq_2f85.py
mujoco_controllers/models/robot_arm.py
mujoco_controllers/mujoco_menagerie/.git
mujoco_controllers/mujoco_menagerie/.github/ISSUE_TEMPLATE/bug_report.md
mujoco_controllers-0.0.2.dist-info/LICENSE
mujoco_controllers-0.0.2.dist-info/METADATA
mujoco_controllers-0.0.2.dist-info/WHEEL
mujoco_controllers-0.0.2.dist-info/RECORD
