Metadata-Version: 2.1
Name: mujoco_controllers
Version: 0.0.2
Summary: A repository for debugging controller implementations applied to mujoco models.
License: Apache-2.0
Author: Peter David Fagan
Author-email: peterdavidfagan@gmail.com
Requires-Python: >=3.10.6,<4.0.0
Classifier: License :: OSI Approved :: Apache Software License
Classifier: Programming Language :: Python :: 3
Classifier: Programming Language :: Python :: 3.11
Classifier: Programming Language :: Python :: 3.12
Requires-Dist: dm-control (>=1.0.16,<2.0.0)
Requires-Dist: hydra-core (>=1.3.2,<2.0.0)
Requires-Dist: ipywidgets (>=8.1.1,<9.0.0)
Requires-Dist: jax (>=0.4.14,<0.5.0)
Requires-Dist: jaxopt (>=0.8.2,<0.9.0)
Requires-Dist: jupyterlab (>=4.0.9,<5.0.0)
Requires-Dist: lark (>=1.1.7,<2.0.0)
Requires-Dist: matplotlib (>=3.7.2,<4.0.0)
Requires-Dist: mujoco (>=3.1.1,<4.0.0)
Requires-Dist: notebook (>=7.0.6,<8.0.0)
Requires-Dist: numpy (>=1.16.0,<2.0.0)
Requires-Dist: pandas (>=2.1.3,<3.0.0)
Requires-Dist: pillow (==10.0.0)
Requires-Dist: plotly (>=5.18.0,<6.0.0)
Requires-Dist: profilehooks (>=1.12.0,<2.0.0)
Requires-Dist: pytest (>=7.4.2,<8.0.0)
